tests/__init__.py
tests/test_converter.py
video2livephoto/__init__.py
video2livephoto/converter.py
video2livephoto-0.1.0.dist-info/LICENSE
video2livephoto-0.1.0.dist-info/METADATA
video2livephoto-0.1.0.dist-info/WHEEL
video2livephoto-0.1.0.dist-info/top_level.txt
video2livephoto-0.1.0.dist-info/RECORD
