Metadata-Version: 2.1
Name: video2livephoto
Version: 0.1.0
Summary: Um pacote para converter vídeos em live-fotos, comum em dispositivos iOS.
Home-page: https://github.com/seu_usuario/video2livephoto
Author: Ródiney Wanderson
Author-email: rodineyw@yahoo.com.br
Classifier: Development Status :: 3 - Alpha
Classifier: Intended Audience :: Developers
Classifier: Topic :: Software Development :: Build Tools
Classifier: License :: OSI Approved :: MIT License
Classifier: Programming Language :: Python :: 3
Classifier: Programming Language :: Python :: 3.7
Classifier: Programming Language :: Python :: 3.8
Classifier: Programming Language :: Python :: 3.9
Classifier: Programming Language :: Python :: 3.10
Classifier: Programming Language :: Python :: 3.11
Classifier: Programming Language :: Python :: 3.12
Requires-Python: >=3.7
License-File: LICENSE
Requires-Dist: opencv-python
Requires-Dist: Pillow
